README.md
setup.py
locuscomplexity/__init__.py
locuscomplexity/color_code.py
locuscomplexity/complexity.py
locuscomplexity/fitness.py
locuscomplexity.egg-info/PKG-INFO
locuscomplexity.egg-info/SOURCES.txt
locuscomplexity.egg-info/dependency_links.txt
locuscomplexity.egg-info/requires.txt
locuscomplexity.egg-info/top_level.txt
locuscomplexity/data/dict_colors.pkl