Metadata-Version: 2.1
Name: locuscomplexity
Version: 0.2.2
Summary: UNKNOWN
Home-page: https://github.com/LocusAnalytics/EconCmplx
License: UNKNOWN
Platform: UNKNOWN
